README.md
setup.cfg
setup.py
edgel3/__init__.py
edgel3/__main__.py
edgel3/cli.py
edgel3/core.py
edgel3/edgel3_exceptions.py
edgel3/edgel3_warnings.py
edgel3/models.py
edgel3/version.py
edgel3.egg-info/PKG-INFO
edgel3.egg-info/SOURCES.txt
edgel3.egg-info/dependency_links.txt
edgel3.egg-info/entry_points.txt
edgel3.egg-info/requires.txt
edgel3.egg-info/top_level.txt
tests/__init__.py
tests/test_cli.py
tests/test_core.py
tests/test_models.py