Metadata-Version: 2.1
Name: edgel3
Version: 0.2.1
Summary: Audio embeddings based on sparse or UST specialized (SEA) Look, Listen, and Learn (L3) models for the Edge
Home-page: https://github.com/ksangeeta2429/edgel3
Author: Sangeeta Srivastava
Author-email: sangeeta.osu@gmail.com
License: MIT
Project-URL: Source, https://github.com/ksangeeta2429/edgel3
Project-URL: Tracker, https://github.com/ksangeeta2429/edgel3/issues
Project-URL: Documentation, https://readthedocs.org/projects/edgel3/
Keywords: audio embeddings machine learning tensorflow keras pruning compression embedding approximation knowledge distillation
Platform: UNKNOWN
Classifier: Development Status :: 2 - Pre-Alpha
Classifier: License :: OSI Approved :: MIT License
Classifier: Intended Audience :: Developers
Classifier: Intended Audience :: Science/Research
Classifier: Topic :: Multimedia :: Sound/Audio :: Analysis
Classifier: Programming Language :: Python :: 3
Classifier: Programming Language :: Python :: 3.6
Classifier: Programming Language :: Python :: 3.7
Classifier: Programming Language :: Python :: 3.8
Provides-Extra: docs
Provides-Extra: tests
